corpussearch/__init__.py
corpussearch/base.py
corpussearch/gui.py
corpussearch/ml.py
corpussearch/vis.py
corpussearch/tests/__init__.py
corpussearch/tests/test_corpussearch.py
corpussearch-0.0.16.dist-info/DESCRIPTION.rst
corpussearch-0.0.16.dist-info/METADATA
corpussearch-0.0.16.dist-info/RECORD
corpussearch-0.0.16.dist-info/WHEEL
corpussearch-0.0.16.dist-info/metadata.json
corpussearch-0.0.16.dist-info/top_level.txt
