Metadata-Version: 2.0
Name: corpussearch
Version: 0.0.16
Summary: Tools for loading and analyzing large text corpora.
Home-page: https://github.com/computational-antiquity/corpussearch/
Author: Malte Vogl
Author-email: mvogl@mpiwg-berlin.mpg.de
License: GPLv3
Project-URL: Home, https://github.com/computational-antiquity/corpussearch/
Project-URL: Tracker, https://github.com/computational-antiquity/corpussearch/issues
Project-URL: Download, https://github.com/computational-antiquity/corpussearch/archive/0.0.16.tar.gz
Platform: UNKNOWN
Classifier: Development Status :: 3 - Alpha
Classifier: Intended Audience :: Science/Research
Classifier: Topic :: Text Processing :: General
Classifier: Topic :: Text Processing :: Indexing
Classifier: License :: OSI Approved :: GNU General Public License v3 (GPLv3)
Classifier: Programming Language :: Python :: 3
Requires-Python: >=3
Requires-Dist: pandas
Requires-Dist: numpy
Requires-Dist: xlrd
Requires-Dist: citableclass
Requires-Dist: ipywidgets
Requires-Dist: Ipython
Requires-Dist: gensim
Requires-Dist: cltk
